<?xml version="1.0" encoding="UTF-8"?>
<record_update table="catalog_ui_policy_action">
    <catalog_ui_policy_action action="INSERT_OR_UPDATE">
        <catalog_item display_value="OneSphere - Project Creation">f4b28751db2f530071ec771c8c9619e9</catalog_item>
        <catalog_variable>IO:fbc7f047db67570071ec771c8c96196e</catalog_variable>
        <disabled>ignore</disabled>
        <field/>
        <mandatory>true</mandatory>
        <sys_class_name>catalog_ui_policy_action</sys_class_name>
        <sys_created_by>anando</sys_created_by>
        <sys_created_on>2018-07-31 09:53:26</sys_created_on>
        <sys_id>83787c47db67570071ec771c8c961966</sys_id>
        <sys_mod_count>0</sys_mod_count>
        <sys_name>access_key</sys_name>
        <sys_package display_value="OneSphere Integration" source="x_228286_onesphere">0d703a034f161300fb4cb82ca310c79e</sys_package>
        <sys_policy/>
        <sys_scope display_value="OneSphere Integration">0d703a034f161300fb4cb82ca310c79e</sys_scope>
        <sys_update_name>catalog_ui_policy_action_83787c47db67570071ec771c8c961966</sys_update_name>
        <sys_updated_by>anando</sys_updated_by>
        <sys_updated_on>2018-07-31 09:53:26</sys_updated_on>
        <table/>
        <ui_policy display_value="OneSphere - AWS Access Key">6bf63807db67570071ec771c8c9619ed</ui_policy>
        <variable>access_key</variable>
        <variable_set/>
        <visible>true</visible>
    </catalog_ui_policy_action>
</record_update>
